{"type":"Thing","id":"urn:ngsi-ld:Thing:9432589","relationships":{"observes":{"type":"Relationship","object":"urn:ngsi-ld:WeatherObserved:9432589"}},"thingGroups":{"value":["Anemometers"]},"deviceState":{"type":"Property","value":"OPERATIVO"},"category":{"type":"Property","value":["measurement"]},"location":{"type":"GeoProperty","value":{"type":"Point","coordinates":[447806.02240000013,4479071.4384]}},"@context":"https:\/\/raw.githubusercontent.com\/awslabs\/garnet-framework\/main\/context.jsonld"}