{"type":"Thing","id":"urn:ngsi-ld:Thing:7953919","relationships":{"observes":{"type":"Relationship","object":"urn:ngsi-ld:WeatherObserved:7953919"}},"thingGroups":{"value":["Anemometers"]},"deviceState":{"type":"Property","value":"OPERATIVO"},"category":{"type":"Property","value":["measurement"]},"location":{"type":"GeoProperty","value":{"type":"Point","coordinates":[447811.14580000006,4.473203305E+6]}},"@context":"https:\/\/raw.githubusercontent.com\/awslabs\/garnet-framework\/main\/context.jsonld"}